README.md
setup.py
cuzcatlan/__init__.py
cuzcatlan/ccal_style.py
cuzcatlan/clustering.py
cuzcatlan/elemental.py
cuzcatlan/information.py
cuzcatlan/rnaseq.py
cuzcatlan/statannot.py
cuzcatlan.egg-info/PKG-INFO
cuzcatlan.egg-info/SOURCES.txt
cuzcatlan.egg-info/dependency_links.txt
cuzcatlan.egg-info/not-zip-safe
cuzcatlan.egg-info/requires.txt
cuzcatlan.egg-info/top_level.txt