Metadata-Version: 1.0
Name: cuzcatlan
Version: 0.9.2
Summary: Edwin Juarez's support library for GenePattern.
Home-page: https://github.com/edjuaro/cuzcatlan
Author: Edwin F. Juarez
Author-email: ejuarez@ucsd.edu
License: MIT
Platform: UNKNOWN
